bits/__init__.py
bits/client/__init__.py
bits/client/baseclass.py
bits/client/baseclient.py
bits/client/functions.py
bits/client/parser.py
bits_client-1.0.dist-info/METADATA
bits_client-1.0.dist-info/WHEEL
bits_client-1.0.dist-info/top_level.txt
bits_client-1.0.dist-info/RECORD
