Metadata-Version: 2.1
Name: bits-client
Version: 1.0
Summary: BITS Client
Home-page: UNKNOWN
Author: Lukas Karlsson
Author-email: karlsson@broadinstitute.org
License: Apache Software License
Platform: UNKNOWN
